learn_pyproject/__init__.py
learn_pyproject/hello.py
learn_pyproject-0.1.1.dist-info/LICENSE
learn_pyproject-0.1.1.dist-info/METADATA
learn_pyproject-0.1.1.dist-info/WHEEL
learn_pyproject-0.1.1.dist-info/RECORD
