Metadata-Version: 2.3
Name: learn-pyproject
Version: 0.1.1
Summary: Learn modern Python packaging with Poetry, pyproject.toml and PyPI.
Author: Jordan Blakey
Author-email: 454820+jordanblakey@users.noreply.github.com
Requires-Python: >=3.12
Classifier: Programming Language :: Python :: 3
Classifier: Programming Language :: Python :: 3.12
Classifier: Programming Language :: Python :: 3.13
Requires-Dist: pendulum (>=3.1.0,<4.0.0)
